quickscale_cli/__init__.py
quickscale_cli/_version.py
quickscale_cli/commands/__init__.py
quickscale_cli/commands/apply_command.py
quickscale_cli/commands/deployment_commands.py
quickscale_cli/commands/development_commands.py
quickscale_cli/commands/module_commands.py
quickscale_cli/commands/module_config.py
quickscale_cli/commands/plan_command.py
quickscale_cli/commands/remove_command.py
quickscale_cli/commands/status_command.py
quickscale_cli/main.py
quickscale_cli/schema/__init__.py
quickscale_cli/schema/config_schema.py
quickscale_cli/schema/delta.py
quickscale_cli/schema/state_schema.py
quickscale_cli/utils/__init__.py
quickscale_cli/utils/dependency_utils.py
quickscale_cli/utils/docker_utils.py
quickscale_cli/utils/project_manager.py
quickscale_cli/utils/railway_utils.py
quickscale_cli-0.73.0.dist-info/METADATA
quickscale_cli-0.73.0.dist-info/WHEEL
quickscale_cli-0.73.0.dist-info/entry_points.txt
quickscale_cli-0.73.0.dist-info/RECORD
